main.py
om_db.py
modules/__init__.py
modules/achievements_gallery.py
modules/addiction_recovery.py
modules/affirmations.py
modules/ai_companion.py
modules/anxiety_support.py
modules/api_server.py
modules/ascii_art.py
modules/backup_export.py
modules/body_image_support.py
modules/breathing.py
modules/cbt_toolkit.py
modules/chatbot.py
modules/coping_skills.py
modules/coping_strategies.py
modules/daily_checkin.py
modules/demo_achievements.py
modules/depression_support.py
modules/emotion_analysis.py
modules/enhanced_chatbot.py
modules/enhanced_meditation.py
modules/enhanced_mood_tracking.py
modules/external_integrations.py
modules/gratitude.py
modules/guided_journals.py
modules/habits.py
modules/hypnosis_sessions.py
modules/insomnia_support.py
modules/intention_timer.py
modules/international_crisis.py
modules/learning_paths.py
modules/meditation.py
modules/mental_health_articles.py
modules/mental_health_classifier.py
modules/mental_health_coach.py
modules/mood_tracking.py
modules/neurowave_stimulation.py
modules/nicky_case_guide.py
modules/physical.py
modules/positive_psychology.py
modules/quick_actions.py
modules/quick_capture.py
modules/rescue_sessions.py
modules/sleep_optimization.py
modules/sleep_sounds.py
modules/smart_suggestions.py
modules/social_connection.py
modules/textual_example.py
modules/visual_achievements.py
modules/wellness_autopilot.py
modules/wellness_dashboard.py
modules/wellness_dashboard_enhanced.py
modules/wellness_gamification.py
om_cli-0.1.0.dist-info/licenses/LICENSE
om_cli-0.1.0.dist-info/METADATA
om_cli-0.1.0.dist-info/WHEEL
om_cli-0.1.0.dist-info/entry_points.txt
om_cli-0.1.0.dist-info/top_level.txt
om_cli-0.1.0.dist-info/RECORD
