Metadata-Version: 2.4
Name: om-cli
Version: 0.1.0
Summary: Advanced Mental Health CLI Platform - Privacy-first wellness toolkit with AI coaching, CBT tools, crisis support, and evidence-based interventions
Home-page: https://github.com/frism/om
Author: frism
Author-email: contact@om-cli.org
Project-URL: Homepage, https://github.com/frism/om
Project-URL: Bug Reports, https://github.com/frism/om/issues
Project-URL: Source, https://github.com/frism/om
Project-URL: Documentation, https://github.com/frism/om/tree/main/docs
Project-URL: Funding, https://ko-fi.com/omcli
Keywords: mental-health,wellness,cli,mindfulness,meditation,cbt,therapy,anxiety,depression,self-care,privacy,terminal,coaching,crisis-support,mood-tracking
Classifier: Development Status :: 4 - Beta
Classifier: Intended Audience :: End Users/Desktop
Classifier: Intended Audience :: Healthcare Industry
Classifier: License :: OSI Approved :: MIT License
Classifier: Operating System :: OS Independent
Classifier: Programming Language :: Python :: 3
Classifier: Programming Language :: Python :: 3.11
Classifier: Programming Language :: Python :: 3.12
Classifier: Topic :: Scientific/Engineering :: Medical Science Apps.
Classifier: Topic :: Utilities
Classifier: Topic :: Terminals
Classifier: Environment :: Console
Classifier: Natural Language :: English
Requires-Python: >=3.11
License-File: LICENSE
Requires-Dist: rich>=13.0.0
Requires-Dist: textual>=0.40.0
Requires-Dist: click>=8.0.0
Requires-Dist: colorama>=0.4.6
Requires-Dist: requests>=2.28.0
Requires-Dist: flask>=2.3.0
Requires-Dist: pygame>=2.1.0
Requires-Dist: pytest>=7.0.0
Requires-Dist: sphinx>=5.0.0
Dynamic: author
Dynamic: author-email
Dynamic: classifier
Dynamic: description
Dynamic: description-content-type
Dynamic: home-page
Dynamic: keywords
Dynamic: license-file
Dynamic: project-url
Dynamic: requires-dist
Dynamic: requires-python
Dynamic: summary
